cosecurity_amqp_lib/__init__.py
cosecurity_amqp_lib/client.py
cosecurity_amqp_lib/consumer.py
cosecurity_amqp_lib/logger.py
cosecurity_amqp_lib/producer.py
cosecurity_amqp_lib/stub.py
cosecurity_amqp_lib-1.0.22.dist-info/LICENSE
cosecurity_amqp_lib-1.0.22.dist-info/METADATA
cosecurity_amqp_lib-1.0.22.dist-info/WHEEL
cosecurity_amqp_lib-1.0.22.dist-info/top_level.txt
cosecurity_amqp_lib-1.0.22.dist-info/RECORD
