Metadata-Version: 2.1
Name: cosecurity-amqp-lib
Version: 1.0.22
Summary: This is a package that includes all AMQP handled messages by the CoSecurity infrastructure
Classifier: Programming Language :: Python :: 3
Classifier: License :: OSI Approved :: MIT License
Classifier: Operating System :: OS Independent
Requires-Python: >=3.6
License-File: LICENSE
Requires-Dist: pika
